{
  "empreendimento": {
    "name": "Jerusalem V"
  },
  "index": 558,
  "generatedAt": "2026-04-30T11:57:28.690Z",
  "templatesUsed": 1,
  "formattedResults": [
    {
      "templateIndex": 0,
      "statusCode": 200,
      "descriptor": {
        "selectMap": {
          "M0": "Min(SEL DimTipoLeilao.DscTipoLeilao)"
        },
        "rawSelect": [
          {
            "Kind": 2,
            "Value": "M0",
            "Name": "Min(SEL DimTipoLeilao.DscTipoLeilao)"
          }
        ]
      },
      "warnings": [
        {
          "code": "IgnoredDataReductionAlgorithm",
          "severity": "Warning",
          "message": "A data reduction algorithm was specified but the corresponding grouping does not exist. The data reduction will be ignored for primary, secondary, intersection and scoped."
        }
      ],
      "meaningfulRows": [
        {
          "Min(SEL DimTipoLeilao.DscTipoLeilao)": "A-6"
        }
      ],
      "raw": {
        "results": [
          {
            "jobId": "0",
            "fromCache": false,
            "result": {
              "data": {
                "timestamp": "/Date(1777550248643)/",
                "rootActivityId": "0dce182d-916c-4d13-8a9c-256284ce93b7",
                "descriptor": {
                  "Select": [
                    {
                      "Kind": 2,
                      "Value": "M0",
                      "Name": "Min(SEL DimTipoLeilao.DscTipoLeilao)"
                    }
                  ],
                  "Version": 2
                },
                "dsr": {
                  "Version": 2,
                  "MinorVersion": 1,
                  "DS": [
                    {
                      "N": "DS0",
                      "PH": [
                        {
                          "DM0": [
                            {
                              "S": [
                                {
                                  "N": "M0",
                                  "T": 1
                                }
                              ],
                              "M0": "A-6"
                            }
                          ]
                        }
                      ],
                      "IC": true,
                      "HAD": true,
                      "Msg": [
                        {
                          "Code": "IgnoredDataReductionAlgorithm",
                          "Severity": "Warning",
                          "Message": "A data reduction algorithm was specified but the corresponding grouping does not exist. The data reduction will be ignored for primary, secondary, intersection and scoped."
                        }
                      ]
                    }
                  ]
                },
                "metrics": {
                  "Version": "1.0.0",
                  "Events": [
                    {
                      "Id": "e0c5ffdd-2159-44bc-8dbe-622022416312",
                      "Name": "Execute Semantic Query",
                      "Component": "DSE",
                      "Start": "2026-04-30T11:57:28.6438266Z",
                      "End": "2026-04-30T11:57:28.6751061Z"
                    },
                    {
                      "Id": "33169c63-8b0a-484a-8167-f6ec462635ba",
                      "ParentId": "e0c5ffdd-2159-44bc-8dbe-622022416312",
                      "Name": "Execute DAX Query",
                      "Component": "DSE",
                      "Start": "2026-04-30T11:57:28.6438266Z",
                      "End": "2026-04-30T11:57:28.6751061Z",
                      "Metrics": {
                        "RowCount": 1
                      }
                    },
                    {
                      "Id": "C58765EE-D076-4C04-A9C5-B1F039437097",
                      "ParentId": "33169c63-8b0a-484a-8167-f6ec462635ba",
                      "Name": "Execute Query",
                      "Component": "AS",
                      "Start": "2026-04-30T11:57:28.67Z",
                      "End": "2026-04-30T11:57:28.677Z"
                    },
                    {
                      "Id": "6E9B28FD-A2CC-4616-8E47-8CCB79C042D3",
                      "ParentId": "C58765EE-D076-4C04-A9C5-B1F039437097",
                      "Name": "Serialize Rowset",
                      "Component": "AS",
                      "Start": "2026-04-30T11:57:28.677Z",
                      "End": "2026-04-30T11:57:28.677Z"
                    }
                  ]
                }
              }
            }
          }
        ],
        "jobIds": [
          "0"
        ]
      }
    }
  ]
}
