{
  "empreendimento": {
    "name": "Panorama 08"
  },
  "index": 759,
  "generatedAt": "2026-04-30T11:57:51.849Z",
  "templatesUsed": 1,
  "formattedResults": [
    {
      "templateIndex": 0,
      "statusCode": 200,
      "descriptor": {
        "selectMap": {
          "M0": "Min(SEL DimTipoLeilao.DscTipoLeilao)"
        },
        "rawSelect": [
          {
            "Kind": 2,
            "Value": "M0",
            "Name": "Min(SEL DimTipoLeilao.DscTipoLeilao)"
          }
        ]
      },
      "warnings": [
        {
          "code": "IgnoredDataReductionAlgorithm",
          "severity": "Warning",
          "message": "A data reduction algorithm was specified but the corresponding grouping does not exist. The data reduction will be ignored for primary, secondary, intersection and scoped."
        }
      ],
      "meaningfulRows": [
        {
          "Min(SEL DimTipoLeilao.DscTipoLeilao)": "A-5"
        }
      ],
      "raw": {
        "results": [
          {
            "jobId": "0",
            "fromCache": false,
            "result": {
              "data": {
                "timestamp": "/Date(1777550272649)/",
                "rootActivityId": "67058ef3-1e11-4a72-8970-8ef36807a7d0",
                "descriptor": {
                  "Select": [
                    {
                      "Kind": 2,
                      "Value": "M0",
                      "Name": "Min(SEL DimTipoLeilao.DscTipoLeilao)"
                    }
                  ],
                  "Version": 2
                },
                "dsr": {
                  "Version": 2,
                  "MinorVersion": 1,
                  "DS": [
                    {
                      "N": "DS0",
                      "PH": [
                        {
                          "DM0": [
                            {
                              "S": [
                                {
                                  "N": "M0",
                                  "T": 1
                                }
                              ],
                              "M0": "A-5"
                            }
                          ]
                        }
                      ],
                      "IC": true,
                      "HAD": true,
                      "Msg": [
                        {
                          "Code": "IgnoredDataReductionAlgorithm",
                          "Severity": "Warning",
                          "Message": "A data reduction algorithm was specified but the corresponding grouping does not exist. The data reduction will be ignored for primary, secondary, intersection and scoped."
                        }
                      ]
                    }
                  ]
                },
                "metrics": {
                  "Version": "1.0.0",
                  "Events": [
                    {
                      "Id": "80d255ee-cf24-413b-a7ae-47957a69645e",
                      "Name": "Execute Semantic Query",
                      "Component": "DSE",
                      "Start": "2026-04-30T11:57:52.6497293Z",
                      "End": "2026-04-30T11:57:52.6809932Z"
                    },
                    {
                      "Id": "75efb8be-26b9-475f-b917-98cd5ca41c25",
                      "ParentId": "80d255ee-cf24-413b-a7ae-47957a69645e",
                      "Name": "Execute DAX Query",
                      "Component": "DSE",
                      "Start": "2026-04-30T11:57:52.6497293Z",
                      "End": "2026-04-30T11:57:52.6809932Z",
                      "Metrics": {
                        "RowCount": 1
                      }
                    },
                    {
                      "Id": "470B5FF8-EE11-42C7-8E02-E2291BA7ADC1",
                      "ParentId": "75efb8be-26b9-475f-b917-98cd5ca41c25",
                      "Name": "Execute Query",
                      "Component": "AS",
                      "Start": "2026-04-30T11:57:52.687Z",
                      "End": "2026-04-30T11:57:52.697Z"
                    },
                    {
                      "Id": "1771708B-FB50-4983-90CC-0F56437B4CFF",
                      "ParentId": "470B5FF8-EE11-42C7-8E02-E2291BA7ADC1",
                      "Name": "Serialize Rowset",
                      "Component": "AS",
                      "Start": "2026-04-30T11:57:52.697Z",
                      "End": "2026-04-30T11:57:52.697Z"
                    }
                  ]
                }
              }
            }
          }
        ],
        "jobIds": [
          "0"
        ]
      }
    }
  ]
}
