{
  "empreendimento": {
    "name": "Ventos de Santo Antônio 08"
  },
  "index": 1267,
  "generatedAt": "2026-04-30T11:58:50.927Z",
  "templatesUsed": 1,
  "formattedResults": [
    {
      "templateIndex": 0,
      "statusCode": 200,
      "descriptor": {
        "selectMap": {
          "M0": "Min(SEL DimTipoLeilao.DscTipoLeilao)"
        },
        "rawSelect": [
          {
            "Kind": 2,
            "Value": "M0",
            "Name": "Min(SEL DimTipoLeilao.DscTipoLeilao)"
          }
        ]
      },
      "warnings": [
        {
          "code": "IgnoredDataReductionAlgorithm",
          "severity": "Warning",
          "message": "A data reduction algorithm was specified but the corresponding grouping does not exist. The data reduction will be ignored for primary, secondary, intersection and scoped."
        }
      ],
      "meaningfulRows": [
        {
          "Min(SEL DimTipoLeilao.DscTipoLeilao)": "A-4"
        }
      ],
      "raw": {
        "results": [
          {
            "jobId": "0",
            "fromCache": false,
            "result": {
              "data": {
                "timestamp": "/Date(1777550331546)/",
                "rootActivityId": "a35c871d-df19-4f9d-9047-7cd1f4baf25a",
                "descriptor": {
                  "Select": [
                    {
                      "Kind": 2,
                      "Value": "M0",
                      "Name": "Min(SEL DimTipoLeilao.DscTipoLeilao)"
                    }
                  ],
                  "Version": 2
                },
                "dsr": {
                  "Version": 2,
                  "MinorVersion": 1,
                  "DS": [
                    {
                      "N": "DS0",
                      "PH": [
                        {
                          "DM0": [
                            {
                              "S": [
                                {
                                  "N": "M0",
                                  "T": 1
                                }
                              ],
                              "M0": "A-4"
                            }
                          ]
                        }
                      ],
                      "IC": true,
                      "HAD": true,
                      "Msg": [
                        {
                          "Code": "IgnoredDataReductionAlgorithm",
                          "Severity": "Warning",
                          "Message": "A data reduction algorithm was specified but the corresponding grouping does not exist. The data reduction will be ignored for primary, secondary, intersection and scoped."
                        }
                      ]
                    }
                  ]
                },
                "metrics": {
                  "Version": "1.0.0",
                  "Events": [
                    {
                      "Id": "0e62cd1e-1f78-49ea-a8b5-ea2fb10e1716",
                      "Name": "Execute Semantic Query",
                      "Component": "DSE",
                      "Start": "2026-04-30T11:58:51.5464198Z",
                      "End": "2026-04-30T11:58:51.5936283Z"
                    },
                    {
                      "Id": "3dde8be9-ee21-40ce-b0ca-c16df7346f4b",
                      "ParentId": "0e62cd1e-1f78-49ea-a8b5-ea2fb10e1716",
                      "Name": "Execute DAX Query",
                      "Component": "DSE",
                      "Start": "2026-04-30T11:58:51.5622534Z",
                      "End": "2026-04-30T11:58:51.5936283Z",
                      "Metrics": {
                        "RowCount": 1
                      }
                    },
                    {
                      "Id": "39B4F2A8-AC8C-44F4-A1B0-EBBA648F7559",
                      "ParentId": "3dde8be9-ee21-40ce-b0ca-c16df7346f4b",
                      "Name": "Execute Query",
                      "Component": "AS",
                      "Start": "2026-04-30T11:58:51.583Z",
                      "End": "2026-04-30T11:58:51.593Z"
                    },
                    {
                      "Id": "45902935-E8E6-4872-941E-2C66D8FF1DCC",
                      "ParentId": "39B4F2A8-AC8C-44F4-A1B0-EBBA648F7559",
                      "Name": "Serialize Rowset",
                      "Component": "AS",
                      "Start": "2026-04-30T11:58:51.593Z",
                      "End": "2026-04-30T11:58:51.593Z"
                    }
                  ]
                }
              }
            }
          }
        ],
        "jobIds": [
          "0"
        ]
      }
    }
  ]
}
