{
  "empreendimento": {
    "name": "Faísa III"
  },
  "index": 414,
  "generatedAt": "2026-04-30T11:57:11.116Z",
  "templatesUsed": 1,
  "results": [
    {
      "templateIndex": 0,
      "statusCode": 200,
      "response": {
        "results": [
          {
            "jobId": "0",
            "fromCache": false,
            "result": {
              "data": {
                "timestamp": "/Date(1777550231527)/",
                "rootActivityId": "d534b663-f91e-41e5-a1cf-e95552aa9836",
                "descriptor": {
                  "Select": [
                    {
                      "Kind": 2,
                      "Value": "M0",
                      "Name": "Min(SEL DimTipoLeilao.DscTipoLeilao)"
                    }
                  ],
                  "Version": 2
                },
                "dsr": {
                  "Version": 2,
                  "MinorVersion": 1,
                  "DS": [
                    {
                      "N": "DS0",
                      "PH": [
                        {
                          "DM0": [
                            {
                              "S": [
                                {
                                  "N": "M0",
                                  "T": 1
                                }
                              ],
                              "M0": "LER"
                            }
                          ]
                        }
                      ],
                      "IC": true,
                      "HAD": true,
                      "Msg": [
                        {
                          "Code": "IgnoredDataReductionAlgorithm",
                          "Severity": "Warning",
                          "Message": "A data reduction algorithm was specified but the corresponding grouping does not exist. The data reduction will be ignored for primary, secondary, intersection and scoped."
                        }
                      ]
                    }
                  ]
                },
                "metrics": {
                  "Version": "1.0.0",
                  "Events": [
                    {
                      "Id": "8083d3c6-deac-49fe-acd7-91fb2516652c",
                      "Name": "Execute Semantic Query",
                      "Component": "DSE",
                      "Start": "2026-04-30T11:57:11.5277095Z",
                      "End": "2026-04-30T11:57:11.5589565Z"
                    },
                    {
                      "Id": "5c1fe09f-2fd0-451d-85da-f08f21fad8ea",
                      "ParentId": "8083d3c6-deac-49fe-acd7-91fb2516652c",
                      "Name": "Execute DAX Query",
                      "Component": "DSE",
                      "Start": "2026-04-30T11:57:11.5277095Z",
                      "End": "2026-04-30T11:57:11.5589565Z",
                      "Metrics": {
                        "RowCount": 1
                      }
                    },
                    {
                      "Id": "80ACE435-9ECC-442D-9413-36B76D7C3176",
                      "ParentId": "5c1fe09f-2fd0-451d-85da-f08f21fad8ea",
                      "Name": "Execute Query",
                      "Component": "AS",
                      "Start": "2026-04-30T11:57:11.553Z",
                      "End": "2026-04-30T11:57:11.56Z"
                    },
                    {
                      "Id": "B50A0A97-72CC-4C2E-90B5-3BE85B8CDC9A",
                      "ParentId": "80ACE435-9ECC-442D-9413-36B76D7C3176",
                      "Name": "Serialize Rowset",
                      "Component": "AS",
                      "Start": "2026-04-30T11:57:11.56Z",
                      "End": "2026-04-30T11:57:11.56Z"
                    }
                  ]
                }
              }
            }
          }
        ],
        "jobIds": [
          "0"
        ]
      }
    }
  ]
}
