{
  "metadata": {
    "source_page": "resultados-leiloes-geracao",
    "source_url": "https://portalrelatorios.aneel.gov.br/resultadosLeiloes/leiloesGeracaoPortugues#",
    "report": "dados-do-empreendimento",
    "filter": "empreendimento",
    "filter_value": "Porto Primavera (Eng° Sérgio Motta)",
    "extraction_method": "playwright-visual-crawler",
    "generated_at": "2026-05-06T14:48:08.547Z",
    "crawl_log": "empreendimento=Porto Primavera (Eng° Sérgio Motta)\nslug=porto-primavera-eng-sergio-motta"
  },
  "data": {
    "empreendimento": {
      "nome": "Porto Primavera (Eng° Sérgio Motta)",
      "vendedora": "Companhia Energética de São …",
      "localidade": "Anaurilândia",
      "uf": "MS",
      "fonte": "Hidro",
      "status": "Operação"
    },
    "energia": {
      "potencia_mw": 1.54,
      "garantia_fisica_mwm": 1.02,
      "energia_vendida_mwm": 82
    },
    "financeiro": {
      "preco_rs_mwm": 124.97,
      "desagio_percentual": 0.02,
      "investimento_previsto_rs": {
        "raw": "0K",
        "value": 0
      },
      "atual_ipca_rs": {
        "raw": "0K",
        "value": 0
      }
    },
    "leilao": {
      "numero": "2/2006",
      "tipo": "A-3",
      "data_leilao": "2006-06-29",
      "data_homologacao": "2006-11-28"
    },
    "outorga": {
      "ato": "Contrato de Concessão nº 003/2004",
      "data_outorga": "(Blank)",
      "data_inicio_operacao": "1999-22-01"
    }
  },
  "raw_cards": [
    {
      "label": "Empreendimento",
      "value": "Porto Primavera (Eng° Sérgio Mo…"
    },
    {
      "label": "Vendedora",
      "value": "Companhia Energética de São …"
    },
    {
      "label": "Localidade",
      "value": "Anaurilândia"
    },
    {
      "label": "UF",
      "value": "MS"
    },
    {
      "label": "Fonte",
      "value": "Hidro"
    },
    {
      "label": "Status",
      "value": "Operação"
    },
    {
      "label": "Potência (MW)",
      "value": "1,540"
    },
    {
      "label": "Garantia Física(MWm)",
      "value": "1.02K"
    },
    {
      "label": "Energia Vendida(MWm)",
      "value": "82.00"
    },
    {
      "label": "Preço(R$/MWm)",
      "value": "124.97"
    },
    {
      "label": "Deságio(%)",
      "value": "0.02%"
    },
    {
      "label": "Invest. Previsto(R$)",
      "value": "0K"
    },
    {
      "label": "Atual. IPCA(R$)",
      "value": "0K"
    },
    {
      "label": "Leilão",
      "value": "2/2006"
    },
    {
      "label": "Tipo Leilão",
      "value": "A-3"
    },
    {
      "label": "Data do Leilão",
      "value": "29/06/2006"
    },
    {
      "label": "Data de Homologação",
      "value": "28/11/2006"
    },
    {
      "label": "Ato de Outorga",
      "value": "Contrato de Concessão nº 003/2004"
    },
    {
      "label": "Data de Outorga",
      "value": "(Blank)"
    },
    {
      "label": "Data Início Operação",
      "value": "1/22/1999"
    }
  ]
}