{
  "metadata": {
    "source_page": "resultados-leiloes-geracao",
    "source_url": "https://portalrelatorios.aneel.gov.br/resultadosLeiloes/leiloesGeracaoPortugues#",
    "report": "dados-do-empreendimento",
    "filter": "empreendimento",
    "filter_value": "Santana do Deserto",
    "extraction_method": "playwright-visual-crawler",
    "generated_at": "2026-05-06T15:06:16.588Z",
    "crawl_log": "empreendimento=Santana do Deserto\nslug=santana-do-deserto"
  },
  "data": {
    "empreendimento": {
      "nome": "Santana do Deserto",
      "vendedora": "Central Geradora Hidroeletrica Sant…",
      "localidade": "Santana do Deserto",
      "uf": "MG",
      "fonte": "Hidro",
      "status": "Operação"
    },
    "energia": {
      "potencia_mw": 2,
      "garantia_fisica_mwm": 1.07,
      "energia_vendida_mwm": 0.96
    },
    "financeiro": {
      "preco_rs_mwm": 227.9,
      "desagio_percentual": 8.1,
      "investimento_previsto_rs": {
        "raw": "9,495K",
        "value": 9495
      },
      "atual_ipca_rs": {
        "raw": "14,684K",
        "value": 14684
      }
    },
    "leilao": {
      "numero": "3/2016",
      "tipo": "LER",
      "data_leilao": "2016-09-23",
      "data_homologacao": "2016-12-06"
    },
    "outorga": {
      "ato": "Portaria MME nº 085",
      "data_outorga": "(Blank)",
      "data_inicio_operacao": "2018-25-05"
    }
  },
  "raw_cards": [
    {
      "label": "Empreendimento",
      "value": "Santana do Deserto"
    },
    {
      "label": "Vendedora",
      "value": "Central Geradora Hidroeletrica Sant…"
    },
    {
      "label": "Localidade",
      "value": "Santana do Deserto"
    },
    {
      "label": "UF",
      "value": "MG"
    },
    {
      "label": "Fonte",
      "value": "Hidro"
    },
    {
      "label": "Status",
      "value": "Operação"
    },
    {
      "label": "Potência (MW)",
      "value": "2"
    },
    {
      "label": "Garantia Física(MWm)",
      "value": "1.07"
    },
    {
      "label": "Energia Vendida(MWm)",
      "value": "0.96"
    },
    {
      "label": "Preço(R$/MWm)",
      "value": "227.90"
    },
    {
      "label": "Deságio(%)",
      "value": "8.10%"
    },
    {
      "label": "Invest. Previsto(R$)",
      "value": "9,495K"
    },
    {
      "label": "Atual. IPCA(R$)",
      "value": "14,684K"
    },
    {
      "label": "Leilão",
      "value": "3/2016"
    },
    {
      "label": "Tipo Leilão",
      "value": "LER"
    },
    {
      "label": "Data do Leilão",
      "value": "23/09/2016"
    },
    {
      "label": "Data de Homologação",
      "value": "06/12/2016"
    },
    {
      "label": "Ato de Outorga",
      "value": "Portaria MME nº 085"
    },
    {
      "label": "Data de Outorga",
      "value": "(Blank)"
    },
    {
      "label": "Data Início Operação",
      "value": "5/25/2018"
    }
  ]
}