{
  "metadata": {
    "source_page": "resultados-leiloes-geracao",
    "source_url": "https://portalrelatorios.aneel.gov.br/resultadosLeiloes/leiloesGeracaoPortugues#",
    "report": "dados-do-empreendimento",
    "filter": "empreendimento",
    "filter_value": "Termonordeste",
    "extraction_method": "playwright-visual-crawler",
    "generated_at": "2026-05-06T15:32:58.609Z",
    "crawl_log": "empreendimento=Termonordeste\nslug=termonordeste"
  },
  "data": {
    "empreendimento": {
      "nome": "Termonordeste",
      "vendedora": "Termomanaus, Ltda.",
      "localidade": "João Pessoa",
      "uf": "PB",
      "fonte": "Óleo combustível",
      "status": "Operação"
    },
    "energia": {
      "potencia_mw": 171,
      "garantia_fisica_mwm": 123.8,
      "energia_vendida_mwm": 123
    },
    "financeiro": {
      "preco_rs_mwm": 135.97,
      "desagio_percentual": 3.56,
      "investimento_previsto_rs": {
        "raw": "162,782K",
        "value": 162782
      },
      "atual_ipca_rs": {
        "raw": "446,710K",
        "value": 446710
      }
    },
    "leilao": {
      "numero": "2/2007",
      "tipo": "A-3",
      "data_leilao": "2007-07-26",
      "data_homologacao": "2007-09-04"
    },
    "outorga": {
      "ato": "Portaria MME nº 347",
      "data_outorga": "2007-12-11",
      "data_inicio_operacao": "2010-24-12"
    }
  },
  "raw_cards": [
    {
      "label": "Empreendimento",
      "value": "Termonordeste"
    },
    {
      "label": "Vendedora",
      "value": "Termomanaus, Ltda."
    },
    {
      "label": "Localidade",
      "value": "João Pessoa"
    },
    {
      "label": "UF",
      "value": "PB"
    },
    {
      "label": "Fonte",
      "value": "Óleo combustível"
    },
    {
      "label": "Status",
      "value": "Operação"
    },
    {
      "label": "Potência (MW)",
      "value": "171"
    },
    {
      "label": "Garantia Física(MWm)",
      "value": "123.80"
    },
    {
      "label": "Energia Vendida(MWm)",
      "value": "123.00"
    },
    {
      "label": "Preço(R$/MWm)",
      "value": "135.97"
    },
    {
      "label": "Deságio(%)",
      "value": "3.56%"
    },
    {
      "label": "Invest. Previsto(R$)",
      "value": "162,782K"
    },
    {
      "label": "Atual. IPCA(R$)",
      "value": "446,710K"
    },
    {
      "label": "Leilão",
      "value": "2/2007"
    },
    {
      "label": "Tipo Leilão",
      "value": "A-3"
    },
    {
      "label": "Data do Leilão",
      "value": "26/07/2007"
    },
    {
      "label": "Data de Homologação",
      "value": "04/09/2007"
    },
    {
      "label": "Ato de Outorga",
      "value": "Portaria MME nº 347"
    },
    {
      "label": "Data de Outorga",
      "value": "11/12/2007"
    },
    {
      "label": "Data Início Operação",
      "value": "12/24/2010"
    }
  ]
}