{
  "metadata": {
    "source_page": "resultados-leiloes-geracao",
    "source_url": "https://portalrelatorios.aneel.gov.br/resultadosLeiloes/leiloesGeracaoPortugues#",
    "report": "dados-do-empreendimento",
    "filter": "empreendimento",
    "filter_value": "Vale do São Simão",
    "extraction_method": "playwright-visual-crawler",
    "generated_at": "2026-05-06T15:41:17.877Z",
    "crawl_log": "empreendimento=Vale do São Simão\nslug=vale-do-sao-simao"
  },
  "data": {
    "empreendimento": {
      "nome": "Vale do São Simão",
      "vendedora": "Companhia Energética Vale do …",
      "localidade": "Santa Vitória",
      "uf": "MG",
      "fonte": "Bagaço de Cana",
      "status": "Operação"
    },
    "energia": {
      "potencia_mw": 50,
      "garantia_fisica_mwm": 12.6,
      "energia_vendida_mwm": 12
    },
    "financeiro": {
      "preco_rs_mwm": 59.79,
      "desagio_percentual": 1.98,
      "investimento_previsto_rs": {
        "raw": "72,289K",
        "value": 72289
      },
      "atual_ipca_rs": {
        "raw": "186,056K",
        "value": 186056
      }
    },
    "leilao": {
      "numero": "1/2008",
      "tipo": "LER",
      "data_leilao": "2008-08-14",
      "data_homologacao": "2008-10-07"
    },
    "outorga": {
      "ato": "Portaria MME nº 092",
      "data_outorga": "2009-02-20",
      "data_inicio_operacao": "2010-21-10"
    }
  },
  "raw_cards": [
    {
      "label": "Empreendimento",
      "value": "Vale do São Simão"
    },
    {
      "label": "Vendedora",
      "value": "Companhia Energética Vale do …"
    },
    {
      "label": "Localidade",
      "value": "Santa Vitória"
    },
    {
      "label": "UF",
      "value": "MG"
    },
    {
      "label": "Fonte",
      "value": "Bagaço de Cana"
    },
    {
      "label": "Status",
      "value": "Operação"
    },
    {
      "label": "Potência (MW)",
      "value": "50"
    },
    {
      "label": "Garantia Física(MWm)",
      "value": "12.60"
    },
    {
      "label": "Energia Vendida(MWm)",
      "value": "12.00"
    },
    {
      "label": "Preço(R$/MWm)",
      "value": "59.79"
    },
    {
      "label": "Deságio(%)",
      "value": "1.98%"
    },
    {
      "label": "Invest. Previsto(R$)",
      "value": "72,289K"
    },
    {
      "label": "Atual. IPCA(R$)",
      "value": "186,056K"
    },
    {
      "label": "Leilão",
      "value": "1/2008"
    },
    {
      "label": "Tipo Leilão",
      "value": "LER"
    },
    {
      "label": "Data do Leilão",
      "value": "14/08/2008"
    },
    {
      "label": "Data de Homologação",
      "value": "07/10/2008"
    },
    {
      "label": "Ato de Outorga",
      "value": "Portaria MME nº 092"
    },
    {
      "label": "Data de Outorga",
      "value": "20/02/2009"
    },
    {
      "label": "Data Início Operação",
      "value": "10/21/2010"
    }
  ]
}