{
  "metadata": {
    "source_page": "resultados-leiloes-geracao",
    "source_url": "https://portalrelatorios.aneel.gov.br/resultadosLeiloes/leiloesGeracaoPortugues#",
    "report": "dados-do-empreendimento",
    "filter": "empreendimento",
    "filter_value": "Vazante 2",
    "extraction_method": "playwright-visual-crawler",
    "generated_at": "2026-05-06T15:42:10.534Z",
    "crawl_log": "empreendimento=Vazante 2\nslug=vazante-2"
  },
  "data": {
    "empreendimento": {
      "nome": "Vazante 2",
      "vendedora": "Consórcio Vazante 2",
      "localidade": "Vazante",
      "uf": "MG",
      "fonte": "Fotovoltaica",
      "status": "Operação"
    },
    "energia": {
      "potencia_mw": 30,
      "garantia_fisica_mwm": 6,
      "energia_vendida_mwm": 6
    },
    "financeiro": {
      "preco_rs_mwm": 216.12,
      "desagio_percentual": 17.51,
      "investimento_previsto_rs": {
        "raw": "128,320K",
        "value": 128320
      },
      "atual_ipca_rs": {
        "raw": "235,514K",
        "value": 235514
      }
    },
    "leilao": {
      "numero": "8/2014",
      "tipo": "LER",
      "data_leilao": "2014-10-31",
      "data_homologacao": "2015-01-27"
    },
    "outorga": {
      "ato": "Portaria MME nº 212",
      "data_outorga": "2015-05-14",
      "data_inicio_operacao": "2017-07-12"
    }
  },
  "raw_cards": [
    {
      "label": "Empreendimento",
      "value": "Vazante 2"
    },
    {
      "label": "Vendedora",
      "value": "Consórcio Vazante 2"
    },
    {
      "label": "Localidade",
      "value": "Vazante"
    },
    {
      "label": "UF",
      "value": "MG"
    },
    {
      "label": "Fonte",
      "value": "Fotovoltaica"
    },
    {
      "label": "Status",
      "value": "Operação"
    },
    {
      "label": "Potência (MW)",
      "value": "30"
    },
    {
      "label": "Garantia Física(MWm)",
      "value": "6.00"
    },
    {
      "label": "Energia Vendida(MWm)",
      "value": "6.00"
    },
    {
      "label": "Preço(R$/MWm)",
      "value": "216.12"
    },
    {
      "label": "Deságio(%)",
      "value": "17.51%"
    },
    {
      "label": "Invest. Previsto(R$)",
      "value": "128,320K"
    },
    {
      "label": "Atual. IPCA(R$)",
      "value": "235,514K"
    },
    {
      "label": "Leilão",
      "value": "8/2014"
    },
    {
      "label": "Tipo Leilão",
      "value": "LER"
    },
    {
      "label": "Data do Leilão",
      "value": "31/10/2014"
    },
    {
      "label": "Data de Homologação",
      "value": "27/01/2015"
    },
    {
      "label": "Ato de Outorga",
      "value": "Portaria MME nº 212"
    },
    {
      "label": "Data de Outorga",
      "value": "14/05/2015"
    },
    {
      "label": "Data Início Operação",
      "value": "12/7/2017"
    }
  ]
}